{"schema":"dream_kernel.solve_map.v001","map_path":"/home/frosty40/nano-world-model/experiments/2026-05-06_arc_dream_curriculum_eval_v002_branch_value_projection_repair/maps/0072_8a0b4eeb907ab02e2732.map.txt","sequence_out":"/home/frosty40/nano-world-model/experiments/2026-05-06_dream_kernel_branch_choice_v037_pre_action_oracle/sequences/0072_8a0b4eeb907ab02e2732.dream_sequence.json","scenario":{"name":"arcdream:8a0b4eeb907ab02e2732","solved":true,"final_reward":1.000000,"terminal":true,"steps":11,"planned_actions":["move_entity_0_dx0_dy1_dz0","move_entity_0_dx0_dy1_dz0","move_entity_0_dx1_dy0_dz0","move_entity_0_dx1_dy0_dz0","move_entity_0_dx1_dy0_dz0","move_entity_0_dx0_dy1_dz0","move_entity_0_dx1_dy0_dz0","move_entity_0_dx1_dy0_dz0","move_entity_0_dx0_dy-1_dz0","move_entity_0_dx0_dy-1_dz0","move_entity_0_dx0_dy-1_dz0"],"final_reason":"moved into goal","sequence_file":"0072_8a0b4eeb907ab02e2732.dream_sequence.json","sequence_hash":"3a9bba3a1bea8ed6","branch_rank_top_match":true,"accepted_steps":11,"rejected_steps":0,"invariant_passed":true,"decision_trace":[{"tick_before":0,"agent_position":{"x":1,"y":1,"z":0},"selected_action_id":"move_entity_0_dx0_dy1_dz0","candidates":[{"action_id":"move_entity_0_dx1_dy0_dz0","policy_score":-0.818328,"branch_chrono_y_net":-0.868328,"outcome_accepted":true,"outcome_reward":0.000000,"outcome_terminal":false,"outcome_reason":"moved into empty","next_position":{"x":2,"y":1,"z":0},"revisit_penalty_applied":false,"wait_penalty_applied":false,"selected":false},{"action_id":"move_entity_0_dx0_dy1_dz0","policy_score":0.181672,"branch_chrono_y_net":0.131672,"outcome_accepted":true,"outcome_reward":0.000000,"outcome_terminal":false,"outcome_reason":"moved into empty","next_position":{"x":1,"y":2,"z":0},"revisit_penalty_applied":false,"wait_penalty_applied":false,"selected":true},{"action_id":"move_entity_0_dx0_dy-1_dz0","policy_score":-1.968328,"branch_chrono_y_net":-0.868328,"outcome_accepted":false,"outcome_reward":0.000000,"outcome_terminal":false,"outcome_reason":"blocked by wall","next_position":{"x":1,"y":1,"z":0},"revisit_penalty_applied":true,"wait_penalty_applied":false,"selected":false},{"action_id":"move_entity_0_dx-1_dy0_dz0","policy_score":-1.968328,"branch_chrono_y_net":-0.868328,"outcome_accepted":false,"outcome_reward":0.000000,"outcome_terminal":false,"outcome_reason":"blocked by wall","next_position":{"x":1,"y":1,"z":0},"revisit_penalty_applied":true,"wait_penalty_applied":false,"selected":false},{"action_id":"wait","policy_score":-1.618328,"branch_chrono_y_net":-0.868328,"outcome_accepted":true,"outcome_reward":0.000000,"outcome_terminal":false,"outcome_reason":"wait","next_position":{"x":1,"y":1,"z":0},"revisit_penalty_applied":true,"wait_penalty_applied":true,"selected":false}]},{"tick_before":1,"agent_position":{"x":1,"y":2,"z":0},"selected_action_id":"move_entity_0_dx0_dy1_dz0","candidates":[{"action_id":"move_entity_0_dx1_dy0_dz0","policy_score":-1.494804,"branch_chrono_y_net":-0.394804,"outcome_accepted":false,"outcome_reward":0.000000,"outcome_terminal":false,"outcome_reason":"blocked by wall","next_position":{"x":1,"y":2,"z":0},"revisit_penalty_applied":true,"wait_penalty_applied":false,"selected":false},{"action_id":"move_entity_0_dx0_dy1_dz0","policy_score":-0.594804,"branch_chrono_y_net":-0.644804,"outcome_accepted":true,"outcome_reward":0.000000,"outcome_terminal":false,"outcome_reason":"moved into empty","next_position":{"x":1,"y":3,"z":0},"revisit_penalty_applied":false,"wait_penalty_applied":false,"selected":true},{"action_id":"move_entity_0_dx0_dy-1_dz0","policy_score":-1.300000,"branch_chrono_y_net":-1.000000,"outcome_accepted":true,"outcome_reward":0.000000,"outcome_terminal":false,"outcome_reason":"moved into empty","next_position":{"x":1,"y":1,"z":0},"revisit_penalty_applied":true,"wait_penalty_applied":false,"selected":false},{"action_id":"move_entity_0_dx-1_dy0_dz0","policy_score":-1.494804,"branch_chrono_y_net":-0.394804,"outcome_accepted":false,"outcome_reward":0.000000,"outcome_terminal":false,"outcome_reason":"blocked by wall","next_position":{"x":1,"y":2,"z":0},"revisit_penalty_applied":true,"wait_penalty_applied":false,"selected":false},{"action_id":"wait","policy_score":-1.144804,"branch_chrono_y_net":-0.394804,"outcome_accepted":true,"outcome_reward":0.000000,"outcome_terminal":false,"outcome_reason":"wait","next_position":{"x":1,"y":2,"z":0},"revisit_penalty_applied":true,"wait_penalty_applied":true,"selected":false}]},{"tick_before":2,"agent_position":{"x":1,"y":3,"z":0},"selected_action_id":"move_entity_0_dx1_dy0_dz0","candidates":[{"action_id":"move_entity_0_dx1_dy0_dz0","policy_score":0.132057,"branch_chrono_y_net":0.082057,"outcome_accepted":true,"outcome_reward":0.000000,"outcome_terminal":false,"outcome_reason":"moved into empty","next_position":{"x":2,"y":3,"z":0},"revisit_penalty_applied":false,"wait_penalty_applied":false,"selected":true},{"action_id":"move_entity_0_dx0_dy1_dz0","policy_score":0.132057,"branch_chrono_y_net":0.082057,"outcome_accepted":true,"outcome_reward":0.000000,"outcome_terminal":false,"outcome_reason":"moved into empty","next_position":{"x":1,"y":4,"z":0},"revisit_penalty_applied":false,"wait_penalty_applied":false,"selected":false},{"action_id":"move_entity_0_dx0_dy-1_dz0","policy_score":-0.217943,"branch_chrono_y_net":0.082057,"outcome_accepted":true,"outcome_reward":0.000000,"outcome_terminal":false,"outcome_reason":"moved into empty","next_position":{"x":1,"y":2,"z":0},"revisit_penalty_applied":true,"wait_penalty_applied":false,"selected":false},{"action_id":"move_entity_0_dx-1_dy0_dz0","policy_score":-1.267943,"branch_chrono_y_net":-0.167943,"outcome_accepted":false,"outcome_reward":0.000000,"outcome_terminal":false,"outcome_reason":"blocked by wall","next_position":{"x":1,"y":3,"z":0},"revisit_penalty_applied":true,"wait_penalty_applied":false,"selected":false},{"action_id":"wait","policy_score":-0.917943,"branch_chrono_y_net":-0.167943,"outcome_accepted":true,"outcome_reward":0.000000,"outcome_terminal":false,"outcome_reason":"wait","next_position":{"x":1,"y":3,"z":0},"revisit_penalty_applied":true,"wait_penalty_applied":true,"selected":false}]},{"tick_before":3,"agent_position":{"x":2,"y":3,"z":0},"selected_action_id":"move_entity_0_dx1_dy0_dz0","candidates":[{"action_id":"move_entity_0_dx1_dy0_dz0","policy_score":-0.434660,"branch_chrono_y_net":-0.484661,"outcome_accepted":true,"outcome_reward":0.000000,"outcome_terminal":false,"outcome_reason":"moved into empty","next_position":{"x":3,"y":3,"z":0},"revisit_penalty_applied":false,"wait_penalty_applied":false,"selected":true},{"action_id":"move_entity_0_dx0_dy1_dz0","policy_score":-0.434660,"branch_chrono_y_net":-0.484661,"outcome_accepted":true,"outcome_reward":0.000000,"outcome_terminal":false,"outcome_reason":"moved into empty","next_position":{"x":2,"y":4,"z":0},"revisit_penalty_applied":false,"wait_penalty_applied":false,"selected":false},{"action_id":"move_entity_0_dx0_dy-1_dz0","policy_score":-1.584661,"branch_chrono_y_net":-0.484661,"outcome_accepted":false,"outcome_reward":0.000000,"outcome_terminal":false,"outcome_reason":"blocked by wall","next_position":{"x":2,"y":3,"z":0},"revisit_penalty_applied":true,"wait_penalty_applied":false,"selected":false},{"action_id":"move_entity_0_dx-1_dy0_dz0","policy_score":-1.034660,"branch_chrono_y_net":-0.734661,"outcome_accepted":true,"outcome_reward":0.000000,"outcome_terminal":false,"outcome_reason":"moved into empty","next_position":{"x":1,"y":3,"z":0},"revisit_penalty_applied":true,"wait_penalty_applied":false,"selected":false},{"action_id":"wait","policy_score":-1.234661,"branch_chrono_y_net":-0.484661,"outcome_accepted":true,"outcome_reward":0.000000,"outcome_terminal":false,"outcome_reason":"wait","next_position":{"x":2,"y":3,"z":0},"revisit_penalty_applied":true,"wait_penalty_applied":true,"selected":false}]},{"tick_before":4,"agent_position":{"x":3,"y":3,"z":0},"selected_action_id":"move_entity_0_dx1_dy0_dz0","candidates":[{"action_id":"move_entity_0_dx1_dy0_dz0","policy_score":-0.950000,"branch_chrono_y_net":-1.000000,"outcome_accepted":true,"outcome_reward":0.000000,"outcome_terminal":false,"outcome_reason":"moved into empty","next_position":{"x":4,"y":3,"z":0},"revisit_penalty_applied":false,"wait_penalty_applied":false,"selected":true},{"action_id":"move_entity_0_dx0_dy1_dz0","policy_score":-2.100000,"branch_chrono_y_net":-1.000000,"outcome_accepted":false,"outcome_reward":0.000000,"outcome_terminal":false,"outcome_reason":"blocked by entity","next_position":{"x":3,"y":3,"z":0},"revisit_penalty_applied":true,"wait_penalty_applied":false,"selected":false},{"action_id":"move_entity_0_dx0_dy-1_dz0","policy_score":-2.100000,"branch_chrono_y_net":-1.000000,"outcome_accepted":false,"outcome_reward":0.000000,"outcome_terminal":false,"outcome_reason":"blocked by wall","next_position":{"x":3,"y":3,"z":0},"revisit_penalty_applied":true,"wait_penalty_applied":false,"selected":false},{"action_id":"move_entity_0_dx-1_dy0_dz0","policy_score":-1.300000,"branch_chrono_y_net":-1.000000,"outcome_accepted":true,"outcome_reward":0.000000,"outcome_terminal":false,"outcome_reason":"moved into empty","next_position":{"x":2,"y":3,"z":0},"revisit_penalty_applied":true,"wait_penalty_applied":false,"selected":false},{"action_id":"wait","policy_score":-1.750000,"branch_chrono_y_net":-1.000000,"outcome_accepted":true,"outcome_reward":0.000000,"outcome_terminal":false,"outcome_reason":"wait","next_position":{"x":3,"y":3,"z":0},"revisit_penalty_applied":true,"wait_penalty_applied":true,"selected":false}]},{"tick_before":5,"agent_position":{"x":4,"y":3,"z":0},"selected_action_id":"move_entity_0_dx0_dy1_dz0","candidates":[{"action_id":"move_entity_0_dx1_dy0_dz0","policy_score":-0.377632,"branch_chrono_y_net":-0.427632,"outcome_accepted":true,"outcome_reward":0.000000,"outcome_terminal":false,"outcome_reason":"moved into empty","next_position":{"x":5,"y":3,"z":0},"revisit_penalty_applied":false,"wait_penalty_applied":false,"selected":false},{"action_id":"move_entity_0_dx0_dy1_dz0","policy_score":-0.127632,"branch_chrono_y_net":-0.177632,"outcome_accepted":true,"outcome_reward":0.000000,"outcome_terminal":false,"outcome_reason":"moved into empty","next_position":{"x":4,"y":4,"z":0},"revisit_penalty_applied":false,"wait_penalty_applied":false,"selected":true},{"action_id":"move_entity_0_dx0_dy-1_dz0","policy_score":-1.277632,"branch_chrono_y_net":-0.177632,"outcome_accepted":false,"outcome_reward":0.000000,"outcome_terminal":false,"outcome_reason":"blocked by wall","next_position":{"x":4,"y":3,"z":0},"revisit_penalty_applied":true,"wait_penalty_applied":false,"selected":false},{"action_id":"move_entity_0_dx-1_dy0_dz0","policy_score":-0.477632,"branch_chrono_y_net":-0.177632,"outcome_accepted":true,"outcome_reward":0.000000,"outcome_terminal":false,"outcome_reason":"moved into empty","next_position":{"x":3,"y":3,"z":0},"revisit_penalty_applied":true,"wait_penalty_applied":false,"selected":false},{"action_id":"wait","policy_score":-0.927632,"branch_chrono_y_net":-0.177632,"outcome_accepted":true,"outcome_reward":0.000000,"outcome_terminal":false,"outcome_reason":"wait","next_position":{"x":4,"y":3,"z":0},"revisit_penalty_applied":true,"wait_penalty_applied":true,"selected":false}]},{"tick_before":6,"agent_position":{"x":4,"y":4,"z":0},"selected_action_id":"move_entity_0_dx1_dy0_dz0","candidates":[{"action_id":"move_entity_0_dx1_dy0_dz0","policy_score":-0.796436,"branch_chrono_y_net":-0.846436,"outcome_accepted":true,"outcome_reward":0.000000,"outcome_terminal":false,"outcome_reason":"moved into empty","next_position":{"x":5,"y":4,"z":0},"revisit_penalty_applied":false,"wait_penalty_applied":false,"selected":true},{"action_id":"move_entity_0_dx0_dy1_dz0","policy_score":-1.946436,"branch_chrono_y_net":-0.846436,"outcome_accepted":false,"outcome_reward":0.000000,"outcome_terminal":false,"outcome_reason":"blocked by wall","next_position":{"x":4,"y":4,"z":0},"revisit_penalty_applied":true,"wait_penalty_applied":false,"selected":false},{"action_id":"move_entity_0_dx0_dy-1_dz0","policy_score":-1.146435,"branch_chrono_y_net":-0.846436,"outcome_accepted":true,"outcome_reward":0.000000,"outcome_terminal":false,"outcome_reason":"moved into empty","next_position":{"x":4,"y":3,"z":0},"revisit_penalty_applied":true,"wait_penalty_applied":false,"selected":false},{"action_id":"move_entity_0_dx-1_dy0_dz0","policy_score":-1.946436,"branch_chrono_y_net":-0.846436,"outcome_accepted":false,"outcome_reward":0.000000,"outcome_terminal":false,"outcome_reason":"blocked by entity","next_position":{"x":4,"y":4,"z":0},"revisit_penalty_applied":true,"wait_penalty_applied":false,"selected":false},{"action_id":"wait","policy_score":-1.596436,"branch_chrono_y_net":-0.846436,"outcome_accepted":true,"outcome_reward":0.000000,"outcome_terminal":false,"outcome_reason":"wait","next_position":{"x":4,"y":4,"z":0},"revisit_penalty_applied":true,"wait_penalty_applied":true,"selected":false}]},{"tick_before":7,"agent_position":{"x":5,"y":4,"z":0},"selected_action_id":"move_entity_0_dx1_dy0_dz0","candidates":[{"action_id":"move_entity_0_dx1_dy0_dz0","policy_score":-0.114068,"branch_chrono_y_net":-0.164068,"outcome_accepted":true,"outcome_reward":0.000000,"outcome_terminal":false,"outcome_reason":"moved into empty","next_position":{"x":6,"y":4,"z":0},"revisit_penalty_applied":false,"wait_penalty_applied":false,"selected":true},{"action_id":"move_entity_0_dx0_dy1_dz0","policy_score":-2.100000,"branch_chrono_y_net":-1.000000,"outcome_accepted":false,"outcome_reward":0.000000,"outcome_terminal":false,"outcome_reason":"blocked by wall","next_position":{"x":5,"y":4,"z":0},"revisit_penalty_applied":true,"wait_penalty_applied":false,"selected":false},{"action_id":"move_entity_0_dx0_dy-1_dz0","policy_score":-0.950000,"branch_chrono_y_net":-1.000000,"outcome_accepted":true,"outcome_reward":0.000000,"outcome_terminal":false,"outcome_reason":"moved into empty","next_position":{"x":5,"y":3,"z":0},"revisit_penalty_applied":false,"wait_penalty_applied":false,"selected":false},{"action_id":"move_entity_0_dx-1_dy0_dz0","policy_score":-1.300000,"branch_chrono_y_net":-1.000000,"outcome_accepted":true,"outcome_reward":0.000000,"outcome_terminal":false,"outcome_reason":"moved into empty","next_position":{"x":4,"y":4,"z":0},"revisit_penalty_applied":true,"wait_penalty_applied":false,"selected":false},{"action_id":"wait","policy_score":-1.750000,"branch_chrono_y_net":-1.000000,"outcome_accepted":true,"outcome_reward":0.000000,"outcome_terminal":false,"outcome_reason":"wait","next_position":{"x":5,"y":4,"z":0},"revisit_penalty_applied":true,"wait_penalty_applied":true,"selected":false}]},{"tick_before":8,"agent_position":{"x":6,"y":4,"z":0},"selected_action_id":"move_entity_0_dx0_dy-1_dz0","candidates":[{"action_id":"move_entity_0_dx1_dy0_dz0","policy_score":-0.110000,"branch_chrono_y_net":0.990000,"outcome_accepted":false,"outcome_reward":0.000000,"outcome_terminal":false,"outcome_reason":"blocked by wall","next_position":{"x":6,"y":4,"z":0},"revisit_penalty_applied":true,"wait_penalty_applied":false,"selected":false},{"action_id":"move_entity_0_dx0_dy1_dz0","policy_score":-0.110000,"branch_chrono_y_net":0.990000,"outcome_accepted":false,"outcome_reward":0.000000,"outcome_terminal":false,"outcome_reason":"blocked by wall","next_position":{"x":6,"y":4,"z":0},"revisit_penalty_applied":true,"wait_penalty_applied":false,"selected":false},{"action_id":"move_entity_0_dx0_dy-1_dz0","policy_score":1.040000,"branch_chrono_y_net":0.990000,"outcome_accepted":true,"outcome_reward":0.000000,"outcome_terminal":false,"outcome_reason":"moved into empty","next_position":{"x":6,"y":3,"z":0},"revisit_penalty_applied":false,"wait_penalty_applied":false,"selected":true},{"action_id":"move_entity_0_dx-1_dy0_dz0","policy_score":-0.074728,"branch_chrono_y_net":0.225272,"outcome_accepted":true,"outcome_reward":0.000000,"outcome_terminal":false,"outcome_reason":"moved into empty","next_position":{"x":5,"y":4,"z":0},"revisit_penalty_applied":true,"wait_penalty_applied":false,"selected":false},{"action_id":"wait","policy_score":0.240000,"branch_chrono_y_net":0.990000,"outcome_accepted":true,"outcome_reward":0.000000,"outcome_terminal":false,"outcome_reason":"wait","next_position":{"x":6,"y":4,"z":0},"revisit_penalty_applied":true,"wait_penalty_applied":true,"selected":false}]},{"tick_before":9,"agent_position":{"x":6,"y":3,"z":0},"selected_action_id":"move_entity_0_dx0_dy-1_dz0","candidates":[{"action_id":"move_entity_0_dx1_dy0_dz0","policy_score":-0.932605,"branch_chrono_y_net":0.167395,"outcome_accepted":false,"outcome_reward":0.000000,"outcome_terminal":false,"outcome_reason":"blocked by wall","next_position":{"x":6,"y":3,"z":0},"revisit_penalty_applied":true,"wait_penalty_applied":false,"selected":false},{"action_id":"move_entity_0_dx0_dy1_dz0","policy_score":0.117395,"branch_chrono_y_net":0.417395,"outcome_accepted":true,"outcome_reward":0.000000,"outcome_terminal":false,"outcome_reason":"moved into empty","next_position":{"x":6,"y":4,"z":0},"revisit_penalty_applied":true,"wait_penalty_applied":false,"selected":false},{"action_id":"move_entity_0_dx0_dy-1_dz0","policy_score":0.217395,"branch_chrono_y_net":0.167395,"outcome_accepted":true,"outcome_reward":0.000000,"outcome_terminal":false,"outcome_reason":"moved into empty","next_position":{"x":6,"y":2,"z":0},"revisit_penalty_applied":false,"wait_penalty_applied":false,"selected":true},{"action_id":"move_entity_0_dx-1_dy0_dz0","policy_score":-0.950000,"branch_chrono_y_net":-1.000000,"outcome_accepted":true,"outcome_reward":0.000000,"outcome_terminal":false,"outcome_reason":"moved into empty","next_position":{"x":5,"y":3,"z":0},"revisit_penalty_applied":false,"wait_penalty_applied":false,"selected":false},{"action_id":"wait","policy_score":-0.582605,"branch_chrono_y_net":0.167395,"outcome_accepted":true,"outcome_reward":0.000000,"outcome_terminal":false,"outcome_reason":"wait","next_position":{"x":6,"y":3,"z":0},"revisit_penalty_applied":true,"wait_penalty_applied":true,"selected":false}]},{"tick_before":10,"agent_position":{"x":6,"y":2,"z":0},"selected_action_id":"move_entity_0_dx0_dy-1_dz0","candidates":[{"action_id":"move_entity_0_dx1_dy0_dz0","policy_score":-1.824824,"branch_chrono_y_net":-0.724824,"outcome_accepted":false,"outcome_reward":0.000000,"outcome_terminal":false,"outcome_reason":"blocked by wall","next_position":{"x":6,"y":2,"z":0},"revisit_penalty_applied":true,"wait_penalty_applied":false,"selected":false},{"action_id":"move_entity_0_dx0_dy1_dz0","policy_score":-1.024824,"branch_chrono_y_net":-0.724824,"outcome_accepted":true,"outcome_reward":0.000000,"outcome_terminal":false,"outcome_reason":"moved into empty","next_position":{"x":6,"y":3,"z":0},"revisit_penalty_applied":true,"wait_penalty_applied":false,"selected":false},{"action_id":"move_entity_0_dx0_dy-1_dz0","policy_score":7.050000,"branch_chrono_y_net":1.000000,"outcome_accepted":true,"outcome_reward":1.000000,"outcome_terminal":true,"outcome_reason":"moved into goal","next_position":{"x":6,"y":1,"z":0},"revisit_penalty_applied":false,"wait_penalty_applied":false,"selected":true},{"action_id":"move_entity_0_dx-1_dy0_dz0","policy_score":-1.824824,"branch_chrono_y_net":-0.724824,"outcome_accepted":false,"outcome_reward":0.000000,"outcome_terminal":false,"outcome_reason":"blocked by wall","next_position":{"x":6,"y":2,"z":0},"revisit_penalty_applied":true,"wait_penalty_applied":false,"selected":false},{"action_id":"wait","policy_score":-1.474824,"branch_chrono_y_net":-0.724824,"outcome_accepted":true,"outcome_reward":0.000000,"outcome_terminal":false,"outcome_reason":"wait","next_position":{"x":6,"y":2,"z":0},"revisit_penalty_applied":true,"wait_penalty_applied":true,"selected":false}]}]}}
